garch/__init__.py
garch/garch2.py
garch-0.1.dist-info/DESCRIPTION.rst
garch-0.1.dist-info/METADATA
garch-0.1.dist-info/RECORD
garch-0.1.dist-info/WHEEL
garch-0.1.dist-info/metadata.json
garch-0.1.dist-info/top_level.txt
