Metadata-Version: 2.0
Name: garch
Version: 0.1
Summary: GARCH (2,2)
Home-page: https://github.com/mckennarogers/garch
Author: McKenna Rogers
Author-email: mckenna.rogers@usu.edu
License: UNKNOWN
Platform: UNKNOWN
